{
  "sources": [
    {
      "type": "portal",
      "name": "Bumeran Colombia",
      "kind": "bumeran",
      "url": "https://www.bumeran.com.co/empleos",
      "render_mode": "browser",
      "max_pages": 3,
      "aggressive": true
    },
    {
      "type": "portal",
      "name": "Bumeran Bogota",
      "kind": "bumeran",
      "url": "https://www.bumeran.com.co/empleos/bogota",
      "render_mode": "browser",
      "max_pages": 3,
      "aggressive": true
    },
    {
      "type": "portal",
      "name": "Trabajando Colombia",
      "kind": "trabajando",
      "url": "https://www.trabajando.com.co/empleos",
      "render_mode": "browser",
      "max_pages": 3,
      "aggressive": true
    },
    {
      "type": "portal",
      "name": "Trabajando Bogota",
      "kind": "trabajando",
      "url": "https://www.trabajando.com.co/empleos/bogota",
      "render_mode": "browser",
      "max_pages": 3,
      "aggressive": true
    }
  ],
  "output_dir": "job_extraction_output_browser_probe",
  "db_path": "job_extraction_output_browser_probe/job_extraction.sqlite3"
}
